examon/__init__.py
examon/lib/__init__.py
examon/lib/config/__init__.py
examon/lib/config/config_dir.py
examon/lib/config/config_dir_factory.py
examon/lib/config/json_config_store.py
examon/lib/config/settings_manager.py
examon/lib/config/settings_manager_factory.py
examon/lib/examon_engine.py
examon/lib/examon_engine_factory.py
examon/lib/pip_installer.py
examon/lib/reporting/__init__.py
examon/lib/reporting/results_manager.py
examon/lib/reporting/stats.py
examon/lib/reporting/streak_tracker.py
examon/lib/storage/__init__.py
examon/lib/storage/read/__init__.py
examon/lib/storage/read/content/__init__.py
examon/lib/storage/read/content/in_memory/in_memory.py
examon/lib/storage/read/content/sqlite3/__init__.py
examon/lib/storage/read/content/sqlite3/sqlite3_reader.py
examon/lib/storage/read/examon_reader_factory.py
examon/lib/storage/read/files/__init__.py
examon/lib/storage/read/files/local_file_system_reader.py
examon/lib/storage/read/protocols.py
examon/lib/storage/read/reader.py
examon/lib/storage/read_write/__init__.py
examon/lib/storage/read_write/naming_strategies/__init__.py
examon/lib/storage/read_write/naming_strategies/filename_strategies.py
examon/lib/storage/read_write/question_adapter_factory.py
examon/lib/storage/read_write/sql_db/__init__.py
examon/lib/storage/read_write/sql_db/models.py
examon/lib/storage/read_write/sql_db/question_query.py
examon/lib/storage/write/__init__.py
examon/lib/storage/write/content/__init__.py
examon/lib/storage/write/content/sqlite3/__init__.py
examon/lib/storage/write/content/sqlite3/sqlite3_writer.py
examon/lib/storage/write/examon_writer_factory.py
examon/lib/storage/write/files/__init__.py
examon/lib/storage/write/files/local_file_system_writer.py
examon/lib/storage/write/protocols.py
examon/lib/storage/write/writer.py
examon/lib/utils/__init__.py
examon/lib/utils/logging.py
examon/lib/utils/sql_alchemy_ext.py
examon/main.py
examon/view/__init__.py
examon/view/cli/__init__.py
examon/view/cli/examon_arg_parse.py
examon-0.6.5.dist-info/METADATA
examon-0.6.5.dist-info/WHEEL
examon-0.6.5.dist-info/entry_points.txt
examon-0.6.5.dist-info/RECORD
