Metadata-Version: 2.1
Name: examon
Version: 0.6.5
Summary: 
Author: Jarrod Folino
Author-email: jdfolino@icloud.com
Requires-Python: >=3.9,<3.12
Classifier: Programming Language :: Python :: 3
Classifier: Programming Language :: Python :: 3.9
Classifier: Programming Language :: Python :: 3.10
Classifier: Programming Language :: Python :: 3.11
Requires-Dist: alembic (>=1.11.2,<2.0.0)
Requires-Dist: boto3 (>=1.28.37,<2.0.0)
Requires-Dist: dataclasses-serialization (>=1.3.1,<2.0.0)
Requires-Dist: examon-core (>=1.3.2)
Requires-Dist: inquirer (>=3.1.1,<4.0.0)
Requires-Dist: pygments (>=2.13.0,<3.0.0)
Requires-Dist: pyinputplus (>=0.2.12,<0.3.0)
Requires-Dist: requests (>=2.31.0,<3.0.0)
Requires-Dist: simple-term-menu (==1.6.1)
Requires-Dist: sqlalchemy (>=2.0.19,<3.0.0)
